PrivatePirxcy/__init__.py
PublicPartyBotFinal-1.0.dist-info/METADATA
PublicPartyBotFinal-1.0.dist-info/WHEEL
PublicPartyBotFinal-1.0.dist-info/top_level.txt
PublicPartyBotFinal-1.0.dist-info/RECORD
